[
    {
        "id_destination": 3,
        "destination": "Annecy",
        "price": "434",
        "url": "https://www.booking.com/hotel/fr/appart-neostelia.fr.html?label=gen173nr-1BCAEoggI46AdIM1gEaE2IAQGYAQ24AQfIAQzYAQHoAQGIAgGoAgO4Ar2A5LsGwAIB0gIkZjFiMTI0NWQtYjUyZC00NmE1LWFmNTctZTFlNzIyNmRlMGI32AIF4AIB&sid=f54edc7492fca222c465a621bc2f43c1&aid=304142&ucfs=1&arphpl=1&checkin=2025-01-13&checkout=2025-01-19&dest_id=-1407760&dest_type=city&group_adults=2&req_adults=2&no_rooms=1&group_children=0&req_children=0&hpos=1&hapos=1&sr_order=popularity&nflt=ht_id%3D204&srpvid=52404ee1858811c4&srepoch=1735989205&all_sr_blocks=1208718631_405213935_2_2_0&highlighted_blocks=1208718631_405213935_2_2_0&matching_block_id=1208718631_405213935_2_2_0&sr_pri_blocks=1208718631_405213935_2_2_0__43400&from=searchresults",
        "dans_destination": 1,
        "de_destination_km": 0
    },
    {
        "id_destination": 3,
        "destination": "Annecy",
        "price": "358",
        "url": "https://www.booking.com/hotel/fr/premiere-classe-annecy-cran-gevrier.fr.html?label=gen173nr-1BCAEoggI46AdIM1gEaE2IAQGYAQ24AQfIAQzYAQHoAQGIAgGoAgO4Ar2A5LsGwAIB0gIkZjFiMTI0NWQtYjUyZC00NmE1LWFmNTctZTFlNzIyNmRlMGI32AIF4AIB&sid=f54edc7492fca222c465a621bc2f43c1&aid=304142&ucfs=1&arphpl=1&checkin=2025-01-13&checkout=2025-01-19&dest_id=-1407760&dest_type=city&group_adults=2&req_adults=2&no_rooms=1&group_children=0&req_children=0&hpos=2&hapos=2&sr_order=popularity&nflt=ht_id%3D204&srpvid=52404ee1858811c4&srepoch=1735989205&all_sr_blocks=166484902_191424412_2_2_0&highlighted_blocks=166484902_191424412_2_2_0&matching_block_id=166484902_191424412_2_2_0&sr_pri_blocks=166484902_191424412_2_2_0__35760&from=searchresults",
        "dans_destination": 1,
        "de_destination_km": 0
    },
    {
        "id_destination": 3,
        "destination": "Annecy",
        "price": "603",
        "url": "https://www.booking.com/hotel/fr/les-terrasses-annecy.fr.html?label=gen173nr-1BCAEoggI46AdIM1gEaE2IAQGYAQ24AQfIAQzYAQHoAQGIAgGoAgO4Ar2A5LsGwAIB0gIkZjFiMTI0NWQtYjUyZC00NmE1LWFmNTctZTFlNzIyNmRlMGI32AIF4AIB&sid=f54edc7492fca222c465a621bc2f43c1&aid=304142&ucfs=1&arphpl=1&checkin=2025-01-13&checkout=2025-01-19&dest_id=-1407760&dest_type=city&group_adults=2&req_adults=2&no_rooms=1&group_children=0&req_children=0&hpos=3&hapos=3&sr_order=popularity&nflt=ht_id%3D204&srpvid=52404ee1858811c4&srepoch=1735989205&all_sr_blocks=26505702_380776361_2_2_0&highlighted_blocks=26505702_380776361_2_2_0&matching_block_id=26505702_380776361_2_2_0&sr_pri_blocks=26505702_380776361_2_2_0__60320&from=searchresults",
        "dans_destination": 1,
        "de_destination_km": 0
    },
    {
        "id_destination": 3,
        "destination": "Annecy",
        "price": "406",
        "url": "https://www.booking.com/hotel/fr/appart-city-annecy-seynod.fr.html?label=gen173nr-1BCAEoggI46AdIM1gEaE2IAQGYAQ24AQfIAQzYAQHoAQGIAgGoAgO4Ar2A5LsGwAIB0gIkZjFiMTI0NWQtYjUyZC00NmE1LWFmNTctZTFlNzIyNmRlMGI32AIF4AIB&sid=f54edc7492fca222c465a621bc2f43c1&aid=304142&ucfs=1&arphpl=1&checkin=2025-01-13&checkout=2025-01-19&dest_id=-1407760&dest_type=city&group_adults=2&req_adults=2&no_rooms=1&group_children=0&req_children=0&hpos=4&hapos=4&sr_order=popularity&nflt=ht_id%3D204&srpvid=52404ee1858811c4&srepoch=1735989205&all_sr_blocks=18332721_93713336_0_2_0&highlighted_blocks=18332721_93713336_0_2_0&matching_block_id=18332721_93713336_0_2_0&sr_pri_blocks=18332721_93713336_0_2_0__40560&from=searchresults",
        "dans_destination": 1,
        "de_destination_km": 0
    },
    {
        "id_destination": 3,
        "destination": "Annecy",
        "price": "400",
        "url": "https://www.booking.com/hotel/fr/sejours-affaires-annecy-le-pont-neuf.fr.html?label=gen173nr-1BCAEoggI46AdIM1gEaE2IAQGYAQ24AQfIAQzYAQHoAQGIAgGoAgO4Ar2A5LsGwAIB0gIkZjFiMTI0NWQtYjUyZC00NmE1LWFmNTctZTFlNzIyNmRlMGI32AIF4AIB&sid=f54edc7492fca222c465a621bc2f43c1&aid=304142&ucfs=1&arphpl=1&checkin=2025-01-13&checkout=2025-01-19&dest_id=-1407760&dest_type=city&group_adults=2&req_adults=2&no_rooms=1&group_children=0&req_children=0&hpos=5&hapos=5&sr_order=popularity&nflt=ht_id%3D204&srpvid=52404ee1858811c4&srepoch=1735989205&all_sr_blocks=18592001_99220245_2_2_0&highlighted_blocks=18592001_99220245_2_2_0&matching_block_id=18592001_99220245_2_2_0&sr_pri_blocks=18592001_99220245_2_2_0__40020&from=searchresults",
        "dans_destination": 1,
        "de_destination_km": 0
    },
    {
        "id_destination": 3,
        "destination": "Annecy",
        "price": "828",
        "url": "https://www.booking.com/hotel/fr/splendid-hotel-annecy.fr.html?label=gen173nr-1BCAEoggI46AdIM1gEaE2IAQGYAQ24AQfIAQzYAQHoAQGIAgGoAgO4Ar2A5LsGwAIB0gIkZjFiMTI0NWQtYjUyZC00NmE1LWFmNTctZTFlNzIyNmRlMGI32AIF4AIB&sid=f54edc7492fca222c465a621bc2f43c1&aid=304142&ucfs=1&arphpl=1&checkin=2025-01-13&checkout=2025-01-19&dest_id=-1407760&dest_type=city&group_adults=2&req_adults=2&no_rooms=1&group_children=0&req_children=0&hpos=6&hapos=6&sr_order=popularity&nflt=ht_id%3D204&srpvid=52404ee1858811c4&srepoch=1735989205&all_sr_blocks=22596812_117041894_2_2_0&highlighted_blocks=22596812_117041894_2_2_0&matching_block_id=22596812_117041894_2_2_0&sr_pri_blocks=22596812_117041894_2_2_0__82836&from=searchresults",
        "dans_destination": 1,
        "de_destination_km": 0
    },
    {
        "id_destination": 3,
        "destination": "Annecy",
        "price": "486",
        "url": "https://www.booking.com/hotel/fr/marina-bay-hotels.fr.html?label=gen173nr-1BCAEoggI46AdIM1gEaE2IAQGYAQ24AQfIAQzYAQHoAQGIAgGoAgO4Ar2A5LsGwAIB0gIkZjFiMTI0NWQtYjUyZC00NmE1LWFmNTctZTFlNzIyNmRlMGI32AIF4AIB&sid=f54edc7492fca222c465a621bc2f43c1&aid=304142&ucfs=1&arphpl=1&checkin=2025-01-13&checkout=2025-01-19&dest_id=-1407760&dest_type=city&group_adults=2&req_adults=2&no_rooms=1&group_children=0&req_children=0&hpos=7&hapos=7&sr_order=popularity&nflt=ht_id%3D204&srpvid=52404ee1858811c4&srepoch=1735989205&all_sr_blocks=24211112_115733245_0_2_0&highlighted_blocks=24211112_115733245_0_2_0&matching_block_id=24211112_115733245_0_2_0&sr_pri_blocks=24211112_115733245_0_2_0__48570&from=searchresults",
        "dans_destination": 1,
        "de_destination_km": 0
    },
    {
        "id_destination": 3,
        "destination": "Annecy",
        "price": "550",
        "url": "https://www.booking.com/hotel/fr/hotelalexandra.fr.html?label=gen173nr-1BCAEoggI46AdIM1gEaE2IAQGYAQ24AQfIAQzYAQHoAQGIAgGoAgO4Ar2A5LsGwAIB0gIkZjFiMTI0NWQtYjUyZC00NmE1LWFmNTctZTFlNzIyNmRlMGI32AIF4AIB&sid=f54edc7492fca222c465a621bc2f43c1&aid=304142&ucfs=1&arphpl=1&checkin=2025-01-13&checkout=2025-01-19&dest_id=-1407760&dest_type=city&group_adults=2&req_adults=2&no_rooms=1&group_children=0&req_children=0&hpos=8&hapos=8&sr_order=popularity&nflt=ht_id%3D204&srpvid=52404ee1858811c4&srepoch=1735989205&all_sr_blocks=13951_309366621_0_2_0&highlighted_blocks=13951_309366621_0_2_0&matching_block_id=13951_309366621_0_2_0&sr_pri_blocks=13951_309366621_0_2_0__55020&from=searchresults",
        "dans_destination": 1,
        "de_destination_km": 0
    },
    {
        "id_destination": 3,
        "destination": "Annecy",
        "price": "566",
        "url": "https://www.booking.com/hotel/fr/ibis-annecy-centre-vieille-ville.fr.html?label=gen173nr-1BCAEoggI46AdIM1gEaE2IAQGYAQ24AQfIAQzYAQHoAQGIAgGoAgO4Ar2A5LsGwAIB0gIkZjFiMTI0NWQtYjUyZC00NmE1LWFmNTctZTFlNzIyNmRlMGI32AIF4AIB&sid=f54edc7492fca222c465a621bc2f43c1&aid=304142&ucfs=1&arphpl=1&checkin=2025-01-13&checkout=2025-01-19&dest_id=-1407760&dest_type=city&group_adults=2&req_adults=2&no_rooms=1&group_children=0&req_children=0&hpos=9&hapos=9&sr_order=popularity&nflt=ht_id%3D204&srpvid=52404ee1858811c4&srepoch=1735989205&all_sr_blocks=56932503_94493442_2_34_0&highlighted_blocks=56932503_94493442_2_34_0&matching_block_id=56932503_94493442_2_34_0&sr_pri_blocks=56932503_94493442_2_34_0__56564&from=searchresults",
        "dans_destination": 1,
        "de_destination_km": 0
    },
    {
        "id_destination": 3,
        "destination": "Annecy",
        "price": "667",
        "url": "https://www.booking.com/hotel/fr/adagio-city-aparthotel-annecy-centre.fr.html?label=gen173nr-1BCAEoggI46AdIM1gEaE2IAQGYAQ24AQfIAQzYAQHoAQGIAgGoAgO4Ar2A5LsGwAIB0gIkZjFiMTI0NWQtYjUyZC00NmE1LWFmNTctZTFlNzIyNmRlMGI32AIF4AIB&sid=f54edc7492fca222c465a621bc2f43c1&aid=304142&ucfs=1&arphpl=1&checkin=2025-01-13&checkout=2025-01-19&dest_id=-1407760&dest_type=city&group_adults=2&req_adults=2&no_rooms=1&group_children=0&req_children=0&hpos=10&hapos=10&sr_order=popularity&nflt=ht_id%3D204&srpvid=52404ee1858811c4&srepoch=1735989205&all_sr_blocks=5790703_94277541_3_2_0&highlighted_blocks=5790703_94277541_3_2_0&matching_block_id=5790703_94277541_3_2_0&sr_pri_blocks=5790703_94277541_3_2_0__66692&from=searchresults",
        "dans_destination": 1,
        "de_destination_km": 0
    },
    {
        "id_destination": 3,
        "destination": "Annecy",
        "price": "1427",
        "url": "https://www.booking.com/hotel/fr/imperial-palace.fr.html?label=gen173nr-1BCAEoggI46AdIM1gEaE2IAQGYAQ24AQfIAQzYAQHoAQGIAgGoAgO4Ar2A5LsGwAIB0gIkZjFiMTI0NWQtYjUyZC00NmE1LWFmNTctZTFlNzIyNmRlMGI32AIF4AIB&sid=f54edc7492fca222c465a621bc2f43c1&aid=304142&ucfs=1&arphpl=1&checkin=2025-01-13&checkout=2025-01-19&dest_id=-1407760&dest_type=city&group_adults=2&req_adults=2&no_rooms=1&group_children=0&req_children=0&hpos=11&hapos=11&sr_order=popularity&nflt=ht_id%3D204&srpvid=52404ee1858811c4&srepoch=1735989205&all_sr_blocks=5434032_270549348_2_2_0&highlighted_blocks=5434032_270549348_2_2_0&matching_block_id=5434032_270549348_2_2_0&sr_pri_blocks=5434032_270549348_2_2_0__142740&from=searchresults",
        "dans_destination": 1,
        "de_destination_km": 0
    },
    {
        "id_destination": 3,
        "destination": "Annecy",
        "price": "518",
        "url": "https://www.booking.com/hotel/fr/hotel-des-alpes.fr.html?label=gen173nr-1BCAEoggI46AdIM1gEaE2IAQGYAQ24AQfIAQzYAQHoAQGIAgGoAgO4Ar2A5LsGwAIB0gIkZjFiMTI0NWQtYjUyZC00NmE1LWFmNTctZTFlNzIyNmRlMGI32AIF4AIB&sid=f54edc7492fca222c465a621bc2f43c1&aid=304142&ucfs=1&arphpl=1&checkin=2025-01-13&checkout=2025-01-19&dest_id=-1407760&dest_type=city&group_adults=2&req_adults=2&no_rooms=1&group_children=0&req_children=0&hpos=12&hapos=12&sr_order=popularity&nflt=ht_id%3D204&srpvid=52404ee1858811c4&srepoch=1735989205&all_sr_blocks=62191_195934951_0_2_0&highlighted_blocks=62191_195934951_0_2_0&matching_block_id=62191_195934951_0_2_0&sr_pri_blocks=62191_195934951_0_2_0__51780&from=searchresults",
        "dans_destination": 1,
        "de_destination_km": 0
    },
    {
        "id_destination": 3,
        "destination": "Annecy",
        "price": "785",
        "url": "https://www.booking.com/hotel/fr/le-royal.fr.html?label=gen173nr-1BCAEoggI46AdIM1gEaE2IAQGYAQ24AQfIAQzYAQHoAQGIAgGoAgO4Ar2A5LsGwAIB0gIkZjFiMTI0NWQtYjUyZC00NmE1LWFmNTctZTFlNzIyNmRlMGI32AIF4AIB&sid=f54edc7492fca222c465a621bc2f43c1&aid=304142&ucfs=1&arphpl=1&checkin=2025-01-13&checkout=2025-01-19&dest_id=-1407760&dest_type=city&group_adults=2&req_adults=2&no_rooms=1&group_children=0&req_children=0&hpos=13&hapos=13&sr_order=popularity&nflt=ht_id%3D204&srpvid=52404ee1858811c4&srepoch=1735989205&all_sr_blocks=5364537_88918802_2_2_0&highlighted_blocks=5364537_88918802_2_2_0&matching_block_id=5364537_88918802_2_2_0&sr_pri_blocks=5364537_88918802_2_2_0__78520&from=searchresults",
        "dans_destination": 1,
        "de_destination_km": 0
    },
    {
        "id_destination": 3,
        "destination": "Annecy",
        "price": "1306",
        "url": "https://www.booking.com/hotel/fr/rivage-amp-spa-annecy.fr.html?label=gen173nr-1BCAEoggI46AdIM1gEaE2IAQGYAQ24AQfIAQzYAQHoAQGIAgGoAgO4Ar2A5LsGwAIB0gIkZjFiMTI0NWQtYjUyZC00NmE1LWFmNTctZTFlNzIyNmRlMGI32AIF4AIB&sid=f54edc7492fca222c465a621bc2f43c1&aid=304142&ucfs=1&arphpl=1&checkin=2025-01-13&checkout=2025-01-19&dest_id=-1407760&dest_type=city&group_adults=2&req_adults=2&no_rooms=1&group_children=0&req_children=0&hpos=14&hapos=14&sr_order=popularity&nflt=ht_id%3D204&srpvid=52404ee1858811c4&srepoch=1735989205&all_sr_blocks=720658203_309071608_2_2_0&highlighted_blocks=720658203_309071608_2_2_0&matching_block_id=720658203_309071608_2_2_0&sr_pri_blocks=720658203_309071608_2_2_0__130640&from=searchresults",
        "dans_destination": 1,
        "de_destination_km": 0
    },
    {
        "id_destination": 3,
        "destination": "Annecy",
        "price": "465",
        "url": "https://www.booking.com/hotel/fr/hotel-balladins-annecy-superior.fr.html?label=gen173nr-1BCAEoggI46AdIM1gEaE2IAQGYAQ24AQfIAQzYAQHoAQGIAgGoAgO4Ar2A5LsGwAIB0gIkZjFiMTI0NWQtYjUyZC00NmE1LWFmNTctZTFlNzIyNmRlMGI32AIF4AIB&sid=f54edc7492fca222c465a621bc2f43c1&aid=304142&ucfs=1&arphpl=1&checkin=2025-01-13&checkout=2025-01-19&dest_id=-1407760&dest_type=city&group_adults=2&req_adults=2&no_rooms=1&group_children=0&req_children=0&hpos=15&hapos=15&sr_order=popularity&nflt=ht_id%3D204&srpvid=52404ee1858811c4&srepoch=1735989205&all_sr_blocks=23081417_91467969_2_2_0&highlighted_blocks=23081417_91467969_2_2_0&matching_block_id=23081417_91467969_2_2_0&sr_pri_blocks=23081417_91467969_2_2_0__46473&from=searchresults",
        "dans_destination": 1,
        "de_destination_km": 0
    },
    {
        "id_destination": 3,
        "destination": "Annecy",
        "price": "531",
        "url": "https://www.booking.com/hotel/fr/best-ha-tel-annecy.fr.html?label=gen173nr-1BCAEoggI46AdIM1gEaE2IAQGYAQ24AQfIAQzYAQHoAQGIAgGoAgO4Ar2A5LsGwAIB0gIkZjFiMTI0NWQtYjUyZC00NmE1LWFmNTctZTFlNzIyNmRlMGI32AIF4AIB&sid=f54edc7492fca222c465a621bc2f43c1&aid=304142&ucfs=1&arphpl=1&checkin=2025-01-13&checkout=2025-01-19&dest_id=-1407760&dest_type=city&group_adults=2&req_adults=2&no_rooms=1&group_children=0&req_children=0&hpos=16&hapos=16&sr_order=popularity&nflt=ht_id%3D204&srpvid=52404ee1858811c4&srepoch=1735989205&all_sr_blocks=44247614_388865092_2_2_0&highlighted_blocks=44247614_388865092_2_2_0&matching_block_id=44247614_388865092_2_2_0&sr_pri_blocks=44247614_388865092_2_2_0__53130&from=searchresults",
        "dans_destination": 1,
        "de_destination_km": 0
    },
    {
        "id_destination": 3,
        "destination": "Annecy",
        "price": "756",
        "url": "https://www.booking.com/hotel/fr/annecy-centre-atria.fr.html?label=gen173nr-1BCAEoggI46AdIM1gEaE2IAQGYAQ24AQfIAQzYAQHoAQGIAgGoAgO4Ar2A5LsGwAIB0gIkZjFiMTI0NWQtYjUyZC00NmE1LWFmNTctZTFlNzIyNmRlMGI32AIF4AIB&sid=f54edc7492fca222c465a621bc2f43c1&aid=304142&ucfs=1&arphpl=1&checkin=2025-01-13&checkout=2025-01-19&dest_id=-1407760&dest_type=city&group_adults=2&req_adults=2&no_rooms=1&group_children=0&req_children=0&hpos=17&hapos=17&sr_order=popularity&nflt=ht_id%3D204&srpvid=52404ee1858811c4&srepoch=1735989205&all_sr_blocks=5729729_94276465_2_2_0&highlighted_blocks=5729729_94276465_2_2_0&matching_block_id=5729729_94276465_2_2_0&sr_pri_blocks=5729729_94276465_2_2_0__75624&from=searchresults",
        "dans_destination": 1,
        "de_destination_km": 0
    },
    {
        "id_destination": 3,
        "destination": "Annecy",
        "price": "421",
        "url": "https://www.booking.com/hotel/fr/campanile-annecy.fr.html?label=gen173nr-1BCAEoggI46AdIM1gEaE2IAQGYAQ24AQfIAQzYAQHoAQGIAgGoAgO4Ar2A5LsGwAIB0gIkZjFiMTI0NWQtYjUyZC00NmE1LWFmNTctZTFlNzIyNmRlMGI32AIF4AIB&sid=f54edc7492fca222c465a621bc2f43c1&aid=304142&ucfs=1&arphpl=1&checkin=2025-01-13&checkout=2025-01-19&dest_id=-1407760&dest_type=city&group_adults=2&req_adults=2&no_rooms=1&group_children=0&req_children=0&hpos=18&hapos=18&sr_order=popularity&nflt=ht_id%3D204&srpvid=52404ee1858811c4&srepoch=1735989205&all_sr_blocks=5497010_94106558_2_42_0&highlighted_blocks=5497010_94106558_2_42_0&matching_block_id=5497010_94106558_2_42_0&sr_pri_blocks=5497010_94106558_2_42_0__42120&from=searchresults",
        "dans_destination": 1,
        "de_destination_km": 0
    },
    {
        "id_destination": 3,
        "destination": "Annecy",
        "price": "422",
        "url": "https://www.booking.com/hotel/fr/greet-annecy.fr.html?label=gen173nr-1BCAEoggI46AdIM1gEaE2IAQGYAQ24AQfIAQzYAQHoAQGIAgGoAgO4Ar2A5LsGwAIB0gIkZjFiMTI0NWQtYjUyZC00NmE1LWFmNTctZTFlNzIyNmRlMGI32AIF4AIB&sid=f54edc7492fca222c465a621bc2f43c1&aid=304142&ucfs=1&arphpl=1&checkin=2025-01-13&checkout=2025-01-19&dest_id=-1407760&dest_type=city&group_adults=2&req_adults=2&no_rooms=1&group_children=0&req_children=0&hpos=19&hapos=19&sr_order=popularity&nflt=ht_id%3D204&srpvid=52404ee1858811c4&srepoch=1735989205&all_sr_blocks=53686302_94487685_2_2_0&highlighted_blocks=53686302_94487685_2_2_0&matching_block_id=53686302_94487685_2_2_0&sr_pri_blocks=53686302_94487685_2_2_0__42216&from=searchresults",
        "dans_destination": 1,
        "de_destination_km": 0
    },
    {
        "id_destination": 3,
        "destination": "Annecy",
        "price": "580",
        "url": "https://www.booking.com/hotel/fr/ica-ne.fr.html?label=gen173nr-1BCAEoggI46AdIM1gEaE2IAQGYAQ24AQfIAQzYAQHoAQGIAgGoAgO4Ar2A5LsGwAIB0gIkZjFiMTI0NWQtYjUyZC00NmE1LWFmNTctZTFlNzIyNmRlMGI32AIF4AIB&sid=f54edc7492fca222c465a621bc2f43c1&aid=304142&ucfs=1&arphpl=1&checkin=2025-01-13&checkout=2025-01-19&dest_id=-1407760&dest_type=city&group_adults=2&req_adults=2&no_rooms=1&group_children=0&req_children=0&hpos=20&hapos=20&sr_order=popularity&nflt=ht_id%3D204&srpvid=52404ee1858811c4&srepoch=1735989205&all_sr_blocks=100389101_339929286_2_2_0&highlighted_blocks=100389101_339929286_2_2_0&matching_block_id=100389101_339929286_2_2_0&sr_pri_blocks=100389101_339929286_2_2_0__58020&from=searchresults",
        "dans_destination": 1,
        "de_destination_km": 0
    },
    {
        "id_destination": 3,
        "destination": "Annecy",
        "price": "1083",
        "url": "https://www.booking.com/hotel/fr/le-pelican-annecy1.fr.html?label=gen173nr-1BCAEoggI46AdIM1gEaE2IAQGYAQ24AQfIAQzYAQHoAQGIAgGoAgO4Ar2A5LsGwAIB0gIkZjFiMTI0NWQtYjUyZC00NmE1LWFmNTctZTFlNzIyNmRlMGI32AIF4AIB&sid=f54edc7492fca222c465a621bc2f43c1&aid=304142&ucfs=1&arphpl=1&checkin=2025-01-13&checkout=2025-01-19&dest_id=-1407760&dest_type=city&group_adults=2&req_adults=2&no_rooms=1&group_children=0&req_children=0&hpos=21&hapos=21&sr_order=popularity&nflt=ht_id%3D204&srpvid=52404ee1858811c4&srepoch=1735989205&all_sr_blocks=756018803_332440559_2_2_0&highlighted_blocks=756018803_332440559_2_2_0&matching_block_id=756018803_332440559_2_2_0&sr_pri_blocks=756018803_332440559_2_2_0__108340&from=searchresults",
        "dans_destination": 1,
        "de_destination_km": 0
    },
    {
        "id_destination": 3,
        "destination": "Annecy",
        "price": "379",
        "url": "https://www.booking.com/hotel/fr/fasthotel-seynod.fr.html?label=gen173nr-1BCAEoggI46AdIM1gEaE2IAQGYAQ24AQfIAQzYAQHoAQGIAgGoAgO4Ar2A5LsGwAIB0gIkZjFiMTI0NWQtYjUyZC00NmE1LWFmNTctZTFlNzIyNmRlMGI32AIF4AIB&sid=f54edc7492fca222c465a621bc2f43c1&aid=304142&ucfs=1&arphpl=1&checkin=2025-01-13&checkout=2025-01-19&dest_id=-1407760&dest_type=city&group_adults=2&req_adults=2&no_rooms=1&group_children=0&req_children=0&hpos=22&hapos=22&sr_order=popularity&nflt=ht_id%3D204&srpvid=52404ee1858811c4&srepoch=1735989205&all_sr_blocks=5433501_106932486_0_2_0&highlighted_blocks=5433501_106932486_0_2_0&matching_block_id=5433501_106932486_0_2_0&sr_pri_blocks=5433501_106932486_0_2_0__37944&from=searchresults",
        "dans_destination": 1,
        "de_destination_km": 0
    },
    {
        "id_destination": 3,
        "destination": "Annecy",
        "price": "726",
        "url": "https://www.booking.com/hotel/fr/comforthotelmandallaz.fr.html?label=gen173nr-1BCAEoggI46AdIM1gEaE2IAQGYAQ24AQfIAQzYAQHoAQGIAgGoAgO4Ar2A5LsGwAIB0gIkZjFiMTI0NWQtYjUyZC00NmE1LWFmNTctZTFlNzIyNmRlMGI32AIF4AIB&sid=f54edc7492fca222c465a621bc2f43c1&aid=304142&ucfs=1&arphpl=1&checkin=2025-01-13&checkout=2025-01-19&dest_id=-1407760&dest_type=city&group_adults=2&req_adults=2&no_rooms=1&group_children=0&req_children=0&hpos=23&hapos=23&sr_order=popularity&nflt=ht_id%3D204&srpvid=52404ee1858811c4&srepoch=1735989205&all_sr_blocks=21155604_376288310_2_1_0&highlighted_blocks=21155604_376288310_2_1_0&matching_block_id=21155604_376288310_2_1_0&sr_pri_blocks=21155604_376288310_2_1_0__72616&from=searchresults",
        "dans_destination": 1,
        "de_destination_km": 0
    },
    {
        "id_destination": 3,
        "destination": "Annecy",
        "price": "586",
        "url": "https://www.booking.com/hotel/fr/campanile-annecy-centre-gare.fr.html?label=gen173nr-1BCAEoggI46AdIM1gEaE2IAQGYAQ24AQfIAQzYAQHoAQGIAgGoAgO4Ar2A5LsGwAIB0gIkZjFiMTI0NWQtYjUyZC00NmE1LWFmNTctZTFlNzIyNmRlMGI32AIF4AIB&sid=f54edc7492fca222c465a621bc2f43c1&aid=304142&ucfs=1&arphpl=1&checkin=2025-01-13&checkout=2025-01-19&dest_id=-1407760&dest_type=city&group_adults=2&req_adults=2&no_rooms=1&group_children=0&req_children=0&hpos=24&hapos=24&sr_order=popularity&nflt=ht_id%3D204&srpvid=52404ee1858811c4&srepoch=1735989205&all_sr_blocks=137772801_93780648_2_2_0&highlighted_blocks=137772801_93780648_2_2_0&matching_block_id=137772801_93780648_2_2_0&sr_pri_blocks=137772801_93780648_2_2_0__58560&from=searchresults",
        "dans_destination": 1,
        "de_destination_km": 0
    },
    {
        "id_destination": 3,
        "destination": "Annecy",
        "price": "593",
        "url": "https://www.booking.com/hotel/fr/logis-de-france-novel-rest-la-mamma.fr.html?label=gen173nr-1BCAEoggI46AdIM1gEaE2IAQGYAQ24AQfIAQzYAQHoAQGIAgGoAgO4Ar2A5LsGwAIB0gIkZjFiMTI0NWQtYjUyZC00NmE1LWFmNTctZTFlNzIyNmRlMGI32AIF4AIB&sid=f54edc7492fca222c465a621bc2f43c1&aid=304142&ucfs=1&arphpl=1&checkin=2025-01-13&checkout=2025-01-19&dest_id=-1407760&dest_type=city&group_adults=2&req_adults=2&no_rooms=1&group_children=0&req_children=0&hpos=25&hapos=25&sr_order=popularity&nflt=ht_id%3D204&srpvid=52404ee1858811c4&srepoch=1735989205&all_sr_blocks=5518602_365571562_0_2_0&highlighted_blocks=5518602_365571562_0_2_0&matching_block_id=5518602_365571562_0_2_0&sr_pri_blocks=5518602_365571562_0_2_0__59320&from=searchresults",
        "dans_destination": 1,
        "de_destination_km": 0
    }
]